bgmi/__init__.py
bgmi/__main__.py
bgmi/config.py
bgmi/main.py
bgmi/namespace.py
bgmi/script.py
bgmi/session.py
bgmi/setup.py
bgmi/downloader/__init__.py
bgmi/downloader/aria2_rpc.py
bgmi/downloader/deluge.py
bgmi/downloader/qbittorrent.py
bgmi/downloader/transmission.py
bgmi/front/__init__.py
bgmi/front/admin.py
bgmi/front/base.py
bgmi/front/index.py
bgmi/front/resources.py
bgmi/front/server.py
bgmi/front/templates/download.xml
bgmi/lib/__init__.py
bgmi/lib/constants.py
bgmi/lib/controllers.py
bgmi/lib/download.py
bgmi/lib/fetch.py
bgmi/lib/models.py
bgmi/lib/update.py
bgmi/others/cron.vbs
bgmi/others/crontab.sh
bgmi/others/me.ricterz.bgmi.plist
bgmi/others/nginx.conf
bgmi/plugin/__init__.py
bgmi/plugin/download.py
bgmi/utils/__init__.py
bgmi/website/__init__.py
bgmi/website/bangumi_moe.py
bgmi/website/base.py
bgmi/website/mikan.py
bgmi/website/model.py
bgmi/website/share_dmhy.py
bgmi-4.5.1.dist-info/entry_points.txt
bgmi-4.5.1.dist-info/licenses/LICENSE
bgmi-4.5.1.dist-info/WHEEL
bgmi-4.5.1.dist-info/METADATA
bgmi-4.5.1.dist-info/RECORD
