Metadata-Version: 2.4
Name: bgmi
Version: 4.5.1
Summary: BGmi is a cli tool for subscribed bangumi.
Keywords: bangumi,bgmi,feed
Author-email: RicterZ <ricterzheng@gmail.com>
Maintainer-email: Trim21 <i@trim21.me>
Requires-Python: >=3.9,<4
License-Expression: MIT
Classifier: Development Status :: 4 - Beta
Classifier: Intended Audience :: Other Audience
Classifier: Natural Language :: Chinese (Traditional)
Classifier: Programming Language :: Python
Classifier: Programming Language :: Python :: 3.8
Classifier: Programming Language :: Python :: 3.9
Classifier: Programming Language :: Python :: 3.10
Classifier: Programming Language :: Python :: 3.11
Classifier: Programming Language :: Python :: Implementation :: CPython
Classifier: Programming Language :: Python :: Implementation :: PyPy
License-File: LICENSE
Requires-Dist: anime-episode-parser (==0.0.13)
Requires-Dist: beautifulsoup4 (==4.13.4)
Requires-Dist: click (==8.1.8)
Requires-Dist: filetype (==1.2.0)
Requires-Dist: icalendar (==6.3.1)
Requires-Dist: loguru (==0.7.3)
Requires-Dist: peewee (==3.18.3)
Requires-Dist: pycomplete (==0.4.0)
Requires-Dist: pydantic (==1.10.22)
Requires-Dist: qbittorrent-api (==2025.5.0)
Requires-Dist: requests (==2.32.4)
Requires-Dist: semver (==3.0.4)
Requires-Dist: stevedore (==5.4.1)
Requires-Dist: strenum (==0.4.15)
Requires-Dist: strsimpy (==0.2.1)
Requires-Dist: tomlkit (==0.13.3)
Requires-Dist: tornado (==6.5)
Requires-Dist: transmission-rpc (==7.0.11)
Requires-Dist: wcwidth (>=0.2.13,<0.3.0)
Requires-Dist: yarl==1.19.0
Project-URL: homepage, https://github.com/BGmi/BGmi
Project-URL: repository, https://github.com/BGmi/BGmi
